{
	"configurations" : 
	[
		{
			"directories" : 
			[
				{
					"build" : ".",
					"childIndexes" : 
					[
						1,
						10
					],
					"hasInstallRule" : true,
					"jsonFile" : "directory-.-Debug-f5ebdc15457944623624.json",
					"minimumCMakeVersion" : 
					{
						"string" : "3.14"
					},
					"projectIndex" : 0,
					"source" : "."
				},
				{
					"build" : "src",
					"childIndexes" : 
					[
						2,
						5,
						7
					],
					"hasInstallRule" : true,
					"jsonFile" : "directory-src-Debug-b6cf2213fc5053b67c22.json",
					"minimumCMakeVersion" : 
					{
						"string" : "3.14"
					},
					"parentIndex" : 0,
					"projectIndex" : 0,
					"source" : "src"
				},
				{
					"build" : "src/lobpcgxx",
					"childIndexes" : 
					[
						3,
						4
					],
					"hasInstallRule" : true,
					"jsonFile" : "directory-src.lobpcgxx-Debug-eb34bfa8e6835d6e39c9.json",
					"minimumCMakeVersion" : 
					{
						"string" : "3.17"
					},
					"parentIndex" : 1,
					"projectIndex" : 1,
					"source" : "src/lobpcgxx",
					"targetIndexes" : 
					[
						0,
						1,
						2,
						3,
						4,
						5,
						6,
						7,
						8,
						9,
						10,
						11,
						12,
						13,
						14,
						15,
						16,
						17,
						18,
						19,
						20,
						21,
						22,
						23,
						24,
						25,
						26,
						27
					]
				},
				{
					"build" : "_deps/blaspp-build",
					"hasInstallRule" : true,
					"jsonFile" : "directory-_deps.blaspp-build-Debug-99d08635922ddbf90e05.json",
					"minimumCMakeVersion" : 
					{
						"string" : "3.17"
					},
					"parentIndex" : 2,
					"projectIndex" : 2,
					"source" : "build/_deps/blaspp-src",
					"targetIndexes" : 
					[
						28
					]
				},
				{
					"build" : "_deps/lapackpp-build",
					"hasInstallRule" : true,
					"jsonFile" : "directory-_deps.lapackpp-build-Debug-761712362d84292c332e.json",
					"minimumCMakeVersion" : 
					{
						"string" : "3.17"
					},
					"parentIndex" : 2,
					"projectIndex" : 3,
					"source" : "build/_deps/lapackpp-src",
					"targetIndexes" : 
					[
						29
					]
				},
				{
					"build" : "src/sparsexx",
					"childIndexes" : 
					[
						6
					],
					"hasInstallRule" : true,
					"jsonFile" : "directory-src.sparsexx-Debug-0357514636ba5461b9d1.json",
					"minimumCMakeVersion" : 
					{
						"string" : "3.18"
					},
					"parentIndex" : 1,
					"projectIndex" : 4,
					"source" : "src/sparsexx",
					"targetIndexes" : 
					[
						34
					]
				},
				{
					"build" : "src/sparsexx/examples",
					"jsonFile" : "directory-src.sparsexx.examples-Debug-9ee3b10aa5fd4d0e33df.json",
					"minimumCMakeVersion" : 
					{
						"string" : "3.18"
					},
					"parentIndex" : 5,
					"projectIndex" : 4,
					"source" : "src/sparsexx/examples",
					"targetIndexes" : 
					[
						36
					]
				},
				{
					"build" : "src/macis",
					"childIndexes" : 
					[
						8,
						9
					],
					"hasInstallRule" : true,
					"jsonFile" : "directory-src.macis-Debug-2febe0a374f86e1c6339.json",
					"minimumCMakeVersion" : 
					{
						"string" : "3.14"
					},
					"parentIndex" : 1,
					"projectIndex" : 0,
					"source" : "src/macis",
					"targetIndexes" : 
					[
						30
					]
				},
				{
					"build" : "_deps/spdlog-build",
					"hasInstallRule" : true,
					"jsonFile" : "directory-_deps.spdlog-build-Debug-837b1f82b64f75153270.json",
					"minimumCMakeVersion" : 
					{
						"string" : "3.11"
					},
					"parentIndex" : 7,
					"projectIndex" : 5,
					"source" : "build/_deps/spdlog-src",
					"targetIndexes" : 
					[
						35
					]
				},
				{
					"build" : "_deps/mdspan-build",
					"hasInstallRule" : true,
					"jsonFile" : "directory-_deps.mdspan-build-Debug-a706443484833088b52c.json",
					"minimumCMakeVersion" : 
					{
						"string" : "3.14"
					},
					"parentIndex" : 7,
					"projectIndex" : 6,
					"source" : "build/_deps/mdspan-src"
				},
				{
					"build" : "tests",
					"childIndexes" : 
					[
						11
					],
					"jsonFile" : "directory-tests-Debug-b01f6abb0ab61427ef3b.json",
					"minimumCMakeVersion" : 
					{
						"string" : "3.14"
					},
					"parentIndex" : 0,
					"projectIndex" : 0,
					"source" : "tests",
					"targetIndexes" : 
					[
						31,
						32,
						33,
						37,
						38
					]
				},
				{
					"build" : "_deps/catch2-build",
					"jsonFile" : "directory-_deps.catch2-build-Debug-b1208c190cea666efc56.json",
					"minimumCMakeVersion" : 
					{
						"string" : "3.5"
					},
					"parentIndex" : 10,
					"projectIndex" : 7,
					"source" : "build/_deps/catch2-src"
				}
			],
			"name" : "Debug",
			"projects" : 
			[
				{
					"childIndexes" : 
					[
						1,
						4,
						5,
						6,
						7
					],
					"directoryIndexes" : 
					[
						0,
						1,
						7,
						10
					],
					"name" : "MACIS",
					"targetIndexes" : 
					[
						30,
						31,
						32,
						33,
						37,
						38
					]
				},
				{
					"childIndexes" : 
					[
						2,
						3
					],
					"directoryIndexes" : 
					[
						2
					],
					"name" : "lobpcgxx",
					"parentIndex" : 0,
					"targetIndexes" : 
					[
						0,
						1,
						2,
						3,
						4,
						5,
						6,
						7,
						8,
						9,
						10,
						11,
						12,
						13,
						14,
						15,
						16,
						17,
						18,
						19,
						20,
						21,
						22,
						23,
						24,
						25,
						26,
						27
					]
				},
				{
					"directoryIndexes" : 
					[
						3
					],
					"name" : "blaspp",
					"parentIndex" : 1,
					"targetIndexes" : 
					[
						28
					]
				},
				{
					"directoryIndexes" : 
					[
						4
					],
					"name" : "lapackpp",
					"parentIndex" : 1,
					"targetIndexes" : 
					[
						29
					]
				},
				{
					"directoryIndexes" : 
					[
						5,
						6
					],
					"name" : "sparsexx",
					"parentIndex" : 0,
					"targetIndexes" : 
					[
						34,
						36
					]
				},
				{
					"directoryIndexes" : 
					[
						8
					],
					"name" : "spdlog",
					"parentIndex" : 0,
					"targetIndexes" : 
					[
						35
					]
				},
				{
					"directoryIndexes" : 
					[
						9
					],
					"name" : "MDSpan",
					"parentIndex" : 0
				},
				{
					"directoryIndexes" : 
					[
						11
					],
					"name" : "Catch2",
					"parentIndex" : 0
				}
			],
			"targets" : 
			[
				{
					"directoryIndex" : 2,
					"id" : "Continuous::@f6e861de985baaa38498",
					"jsonFile" : "target-Continuous-Debug-494c80b6407f8ec15b4b.json",
					"name" : "Continuous",
					"projectIndex" : 1
				},
				{
					"directoryIndex" : 2,
					"id" : "ContinuousBuild::@f6e861de985baaa38498",
					"jsonFile" : "target-ContinuousBuild-Debug-2b97b366e3304f8d8dd2.json",
					"name" : "ContinuousBuild",
					"projectIndex" : 1
				},
				{
					"directoryIndex" : 2,
					"id" : "ContinuousConfigure::@f6e861de985baaa38498",
					"jsonFile" : "target-ContinuousConfigure-Debug-243f355176410de152a3.json",
					"name" : "ContinuousConfigure",
					"projectIndex" : 1
				},
				{
					"directoryIndex" : 2,
					"id" : "ContinuousCoverage::@f6e861de985baaa38498",
					"jsonFile" : "target-ContinuousCoverage-Debug-88fbfef32401b0fb16dc.json",
					"name" : "ContinuousCoverage",
					"projectIndex" : 1
				},
				{
					"directoryIndex" : 2,
					"id" : "ContinuousMemCheck::@f6e861de985baaa38498",
					"jsonFile" : "target-ContinuousMemCheck-Debug-c2131901a38330958d3a.json",
					"name" : "ContinuousMemCheck",
					"projectIndex" : 1
				},
				{
					"directoryIndex" : 2,
					"id" : "ContinuousStart::@f6e861de985baaa38498",
					"jsonFile" : "target-ContinuousStart-Debug-dcdb3c3ed66eba77e156.json",
					"name" : "ContinuousStart",
					"projectIndex" : 1
				},
				{
					"directoryIndex" : 2,
					"id" : "ContinuousSubmit::@f6e861de985baaa38498",
					"jsonFile" : "target-ContinuousSubmit-Debug-795aff7c0ac8c5549386.json",
					"name" : "ContinuousSubmit",
					"projectIndex" : 1
				},
				{
					"directoryIndex" : 2,
					"id" : "ContinuousTest::@f6e861de985baaa38498",
					"jsonFile" : "target-ContinuousTest-Debug-59bfe503d371eb1ad3ae.json",
					"name" : "ContinuousTest",
					"projectIndex" : 1
				},
				{
					"directoryIndex" : 2,
					"id" : "ContinuousUpdate::@f6e861de985baaa38498",
					"jsonFile" : "target-ContinuousUpdate-Debug-90b2ad4765b670048b83.json",
					"name" : "ContinuousUpdate",
					"projectIndex" : 1
				},
				{
					"directoryIndex" : 2,
					"id" : "Experimental::@f6e861de985baaa38498",
					"jsonFile" : "target-Experimental-Debug-b2a5ff54a34aac5b96bb.json",
					"name" : "Experimental",
					"projectIndex" : 1
				},
				{
					"directoryIndex" : 2,
					"id" : "ExperimentalBuild::@f6e861de985baaa38498",
					"jsonFile" : "target-ExperimentalBuild-Debug-4d92aa7d988f99a3850c.json",
					"name" : "ExperimentalBuild",
					"projectIndex" : 1
				},
				{
					"directoryIndex" : 2,
					"id" : "ExperimentalConfigure::@f6e861de985baaa38498",
					"jsonFile" : "target-ExperimentalConfigure-Debug-15ba918edea1ca070f01.json",
					"name" : "ExperimentalConfigure",
					"projectIndex" : 1
				},
				{
					"directoryIndex" : 2,
					"id" : "ExperimentalCoverage::@f6e861de985baaa38498",
					"jsonFile" : "target-ExperimentalCoverage-Debug-5c1245354f54bd6b0c26.json",
					"name" : "ExperimentalCoverage",
					"projectIndex" : 1
				},
				{
					"directoryIndex" : 2,
					"id" : "ExperimentalMemCheck::@f6e861de985baaa38498",
					"jsonFile" : "target-ExperimentalMemCheck-Debug-85bd0167771c1e6d2dba.json",
					"name" : "ExperimentalMemCheck",
					"projectIndex" : 1
				},
				{
					"directoryIndex" : 2,
					"id" : "ExperimentalStart::@f6e861de985baaa38498",
					"jsonFile" : "target-ExperimentalStart-Debug-01cc467e5cd045358fee.json",
					"name" : "ExperimentalStart",
					"projectIndex" : 1
				},
				{
					"directoryIndex" : 2,
					"id" : "ExperimentalSubmit::@f6e861de985baaa38498",
					"jsonFile" : "target-ExperimentalSubmit-Debug-fd1104a696de38557c9c.json",
					"name" : "ExperimentalSubmit",
					"projectIndex" : 1
				},
				{
					"directoryIndex" : 2,
					"id" : "ExperimentalTest::@f6e861de985baaa38498",
					"jsonFile" : "target-ExperimentalTest-Debug-eff2344859d1fab3fe95.json",
					"name" : "ExperimentalTest",
					"projectIndex" : 1
				},
				{
					"directoryIndex" : 2,
					"id" : "ExperimentalUpdate::@f6e861de985baaa38498",
					"jsonFile" : "target-ExperimentalUpdate-Debug-b1feb714c9af37065874.json",
					"name" : "ExperimentalUpdate",
					"projectIndex" : 1
				},
				{
					"directoryIndex" : 2,
					"id" : "Nightly::@f6e861de985baaa38498",
					"jsonFile" : "target-Nightly-Debug-bf67ef4b41c61843e056.json",
					"name" : "Nightly",
					"projectIndex" : 1
				},
				{
					"directoryIndex" : 2,
					"id" : "NightlyBuild::@f6e861de985baaa38498",
					"jsonFile" : "target-NightlyBuild-Debug-553bec8a6e14c1158606.json",
					"name" : "NightlyBuild",
					"projectIndex" : 1
				},
				{
					"directoryIndex" : 2,
					"id" : "NightlyConfigure::@f6e861de985baaa38498",
					"jsonFile" : "target-NightlyConfigure-Debug-59532ec700f671c7fbc5.json",
					"name" : "NightlyConfigure",
					"projectIndex" : 1
				},
				{
					"directoryIndex" : 2,
					"id" : "NightlyCoverage::@f6e861de985baaa38498",
					"jsonFile" : "target-NightlyCoverage-Debug-4d2ad64aebdf769effa7.json",
					"name" : "NightlyCoverage",
					"projectIndex" : 1
				},
				{
					"directoryIndex" : 2,
					"id" : "NightlyMemCheck::@f6e861de985baaa38498",
					"jsonFile" : "target-NightlyMemCheck-Debug-19f5d9df043c84a6fbe6.json",
					"name" : "NightlyMemCheck",
					"projectIndex" : 1
				},
				{
					"directoryIndex" : 2,
					"id" : "NightlyMemoryCheck::@f6e861de985baaa38498",
					"jsonFile" : "target-NightlyMemoryCheck-Debug-5fae7905b9ce0cb424a5.json",
					"name" : "NightlyMemoryCheck",
					"projectIndex" : 1
				},
				{
					"directoryIndex" : 2,
					"id" : "NightlyStart::@f6e861de985baaa38498",
					"jsonFile" : "target-NightlyStart-Debug-89d9867c0dfa8e1ff5d0.json",
					"name" : "NightlyStart",
					"projectIndex" : 1
				},
				{
					"directoryIndex" : 2,
					"id" : "NightlySubmit::@f6e861de985baaa38498",
					"jsonFile" : "target-NightlySubmit-Debug-dcd18310fd6feecd4672.json",
					"name" : "NightlySubmit",
					"projectIndex" : 1
				},
				{
					"directoryIndex" : 2,
					"id" : "NightlyTest::@f6e861de985baaa38498",
					"jsonFile" : "target-NightlyTest-Debug-c8393b41bec52960e246.json",
					"name" : "NightlyTest",
					"projectIndex" : 1
				},
				{
					"directoryIndex" : 2,
					"id" : "NightlyUpdate::@f6e861de985baaa38498",
					"jsonFile" : "target-NightlyUpdate-Debug-bccf0e73e691f9ba5315.json",
					"name" : "NightlyUpdate",
					"projectIndex" : 1
				},
				{
					"directoryIndex" : 3,
					"id" : "blaspp::@58343ecdab427078ad06",
					"jsonFile" : "target-blaspp-Debug-12621e395626d16e01f4.json",
					"name" : "blaspp",
					"projectIndex" : 2
				},
				{
					"directoryIndex" : 4,
					"id" : "lapackpp::@ff4eabba6b54b92c058b",
					"jsonFile" : "target-lapackpp-Debug-caa53d2b1b2be6551a0a.json",
					"name" : "lapackpp",
					"projectIndex" : 3
				},
				{
					"directoryIndex" : 7,
					"id" : "macis::@3f23511e92cb5e41dd93",
					"jsonFile" : "target-macis-Debug-4936adde8d3cb47362df.json",
					"name" : "macis",
					"projectIndex" : 0
				},
				{
					"directoryIndex" : 10,
					"id" : "macis_test::@a44f0ac069e85531cdee",
					"jsonFile" : "target-macis_test-Debug-08e45586b9fcc9341c97.json",
					"name" : "macis_test",
					"projectIndex" : 0
				},
				{
					"directoryIndex" : 10,
					"id" : "simple_driver::@a44f0ac069e85531cdee",
					"jsonFile" : "target-simple_driver-Debug-19f0ea7e1a636e1041a8.json",
					"name" : "simple_driver",
					"projectIndex" : 0
				},
				{
					"directoryIndex" : 10,
					"id" : "simple_driver_dop::@a44f0ac069e85531cdee",
					"jsonFile" : "target-simple_driver_dop-Debug-11174d3448c3862cb71a.json",
					"name" : "simple_driver_dop",
					"projectIndex" : 0
				},
				{
					"directoryIndex" : 5,
					"id" : "sparsexx::@73f47534886deb2a6db0",
					"jsonFile" : "target-sparsexx-Debug-e3e6f9ad69bd60efba5a.json",
					"name" : "sparsexx",
					"projectIndex" : 4
				},
				{
					"directoryIndex" : 8,
					"id" : "spdlog::@eb35cfce7893ccfeff1e",
					"jsonFile" : "target-spdlog-Debug-46d7a7b8f7ac1a81ac77.json",
					"name" : "spdlog",
					"projectIndex" : 5
				},
				{
					"directoryIndex" : 6,
					"id" : "test_dist::@dce4cf1753d8b1b5f812",
					"jsonFile" : "target-test_dist-Debug-5c6613eb7f93e5851638.json",
					"name" : "test_dist",
					"projectIndex" : 4
				},
				{
					"directoryIndex" : 10,
					"id" : "test_drive::@a44f0ac069e85531cdee",
					"jsonFile" : "target-test_drive-Debug-2fc30a636657f9b31b08.json",
					"name" : "test_drive",
					"projectIndex" : 0
				},
				{
					"directoryIndex" : 10,
					"id" : "test_drive_call::@a44f0ac069e85531cdee",
					"jsonFile" : "target-test_drive_call-Debug-5e635b627aab8a4bd9a2.json",
					"name" : "test_drive_call",
					"projectIndex" : 0
				}
			]
		}
	],
	"kind" : "codemodel",
	"paths" : 
	{
		"build" : "/home/diego/Documents/Trabajo/SISSA/Projects/CI_solver/MACIS_mod/build",
		"source" : "/home/diego/Documents/Trabajo/SISSA/Projects/CI_solver/MACIS_mod"
	},
	"version" : 
	{
		"major" : 2,
		"minor" : 6
	}
}
