{
	"backtraceGraph" : 
	{
		"commands" : 
		[
			"install"
		],
		"files" : 
		[
			"build/_deps/blaspp-src/CMakeLists.txt"
		],
		"nodes" : 
		[
			{
				"file" : 0
			},
			{
				"command" : 0,
				"file" : 0,
				"line" : 470,
				"parent" : 0
			},
			{
				"command" : 0,
				"file" : 0,
				"line" : 479,
				"parent" : 0
			},
			{
				"command" : 0,
				"file" : 0,
				"line" : 485,
				"parent" : 0
			},
			{
				"command" : 0,
				"file" : 0,
				"line" : 491,
				"parent" : 0
			},
			{
				"command" : 0,
				"file" : 0,
				"line" : 515,
				"parent" : 0
			}
		]
	},
	"installers" : 
	[
		{
			"backtrace" : 1,
			"component" : "Unspecified",
			"destination" : "lib",
			"paths" : 
			[
				"_deps/blaspp-build/libblaspp.so"
			],
			"targetId" : "blaspp::@58343ecdab427078ad06",
			"targetIndex" : 28,
			"type" : "target"
		},
		{
			"backtrace" : 2,
			"component" : "Unspecified",
			"destination" : "include",
			"paths" : 
			[
				{
					"from" : "build/_deps/blaspp-src/include",
					"to" : "."
				}
			],
			"type" : "directory"
		},
		{
			"backtrace" : 3,
			"component" : "Unspecified",
			"destination" : "include/blas",
			"paths" : 
			[
				"build/_deps/blaspp-build/include/blas/defines.h"
			],
			"type" : "file"
		},
		{
			"backtrace" : 4,
			"component" : "Unspecified",
			"destination" : "lib/blaspp",
			"exportName" : "blasppTargets",
			"exportTargets" : 
			[
				{
					"id" : "blaspp::@58343ecdab427078ad06",
					"index" : 28
				}
			],
			"paths" : 
			[
				"_deps/blaspp-build/CMakeFiles/Export/0646131d0e5e97d3b8a77c1dc54fd44a/blasppTargets.cmake"
			],
			"type" : "export"
		},
		{
			"backtrace" : 5,
			"component" : "Unspecified",
			"destination" : "lib/blaspp",
			"paths" : 
			[
				"build/_deps/blaspp-build/blasppConfig.cmake",
				"build/_deps/blaspp-build/blasppConfigVersion.cmake"
			],
			"type" : "file"
		}
	],
	"paths" : 
	{
		"build" : "_deps/blaspp-build",
		"source" : "build/_deps/blaspp-src"
	}
}
